utf_storage_client/__init__.py
utf_storage_client/api_client.py
utf_storage_client/configuration.py
utf_storage_client/exceptions.py
utf_storage_client/model_utils.py
utf_storage_client/rest.py
utf_storage_client/api/__init__.py
utf_storage_client/api/test_result_api.py
utf_storage_client/apis/__init__.py
utf_storage_client/model/__init__.py
utf_storage_client/model/sqa_test_event.py
utf_storage_client/model/sqa_test_result_record.py
utf_storage_client/model/sqa_test_session_metadata.py
utf_storage_client/model/test_result_input.py
utf_storage_client/model/test_result_storage.py
utf_storage_client/models/__init__.py
utf_storage_client_python-0.1.1.dist-info/METADATA
utf_storage_client_python-0.1.1.dist-info/WHEEL
utf_storage_client_python-0.1.1.dist-info/top_level.txt
utf_storage_client_python-0.1.1.dist-info/RECORD
